jam_pypi/__init__.py
jam_pypi/addition.py
jam_pypi/helper/__init__.py
jam_pypi/helper/division.py
jam_pypi-0.0.7.dist-info/WHEEL
jam_pypi-0.0.7.dist-info/METADATA
jam_pypi-0.0.7.dist-info/RECORD
