Metadata-Version: 2.1
Name: jam-pypi
Version: 0.0.7
Summary: Tesing repo for publish via ci
Keywords: jam,pypi,testing
Author: qsh.27
Author-email: qsh.zh27@gmail.com
Requires-Python: >=3.7,<3.10
Classifier: Programming Language :: Python :: 3
Classifier: Programming Language :: Python :: 3.7
Classifier: Programming Language :: Python :: 3.8
Classifier: Programming Language :: Python :: 3.9
Provides-Extra: exp
Requires-Dist: jamexp (>=0.0.10,<0.0.11); extra == "exp"
Requires-Dist: numpy (>=1.21.2,<2.0.0)
